noscop3r/__init__.py
noscop3r/noscop3r.py
noscop3r-1.1.4.dist-info/METADATA
noscop3r-1.1.4.dist-info/WHEEL
noscop3r-1.1.4.dist-info/entry_points.txt
noscop3r-1.1.4.dist-info/licenses/LICENCE
noscop3r-1.1.4.dist-info/RECORD
