Metadata-Version: 2.3
Name: noScop3r
Version: 1.1.4
Summary: Expand And match IP Addresses
Project-URL: Homepage, https://example.com/noScop3r
Project-URL: Repository, https://github.com/yourusername/noScop3r
Author-email: Jack Mason <jack@jackmason.com>
License-File: LICENCE
Classifier: License :: OSI Approved :: MIT License
Classifier: Operating System :: OS Independent
Classifier: Programming Language :: Python :: 3
Requires-Python: >=3.8
Requires-Dist: colorama
Requires-Dist: netaddr
Requires-Dist: tabulate
